apiverve_emailvalidator/__init__.py
apiverve_emailvalidator/apiClient.py
apiverve_emailvalidator/exceptions.py
apiverve_emailvalidator/setup.py
apiverve_emailvalidator/setup_dep.py
apiverve_emailvalidator/tests/__init__.py
apiverve_emailvalidator/tests/test_api.py
apiverve_emailvalidator-1.1.7.dist-info/LICENSE
apiverve_emailvalidator-1.1.7.dist-info/METADATA
apiverve_emailvalidator-1.1.7.dist-info/WHEEL
apiverve_emailvalidator-1.1.7.dist-info/top_level.txt
apiverve_emailvalidator-1.1.7.dist-info/RECORD
